{
  "page": {
    "id": "n8766lc3ybbs",
    "name": "Atlassian Developer",
    "url": "https://developer.status.atlassian.com",
    "time_zone": "Etc/UTC",
    "updated_at": "2022-04-21T05:56:01.032Z"
  },
  "components": [
    {
      "id": "mlr76v811c20",
      "name": "App listing management",
      "status": "operational",
      "created_at": "2018-02-01T17:46:24.130Z",
      "updated_at": "2022-01-25T12:22:54.237Z",
      "position": 1,
      "description": "The ability to manage app listings on https://marketplace.atlassian.com",
      "showcase": true,
      "start_date": null,
      "group_id": "d0m8l367qqw5",
      "page_id": "n8766lc3ybbs",
      "group": false,
      "only_show_if_degraded": false
    },
    {
      "id": "c1zr70381q86",
      "name": "Bitbucket Cloud APIs",
      "status": "operational",
      "created_at": "2018-02-01T17:15:10.353Z",
      "updated_at": "2018-02-01T17:15:10.353Z",
      "position": 1,
      "description": null,
      "showcase": true,
      "start_date": null,
      "group_id": "w0ld3nc9jvdx",
      "page_id": "n8766lc3ybbs",
      "group": false,
      "only_show_if_degraded": false
    },
    {
      "id": "wzmg8phvmrwh",
      "name": "App Deployment",
      "status": "operational",
      "created_at": "2021-03-23T12:00:27.385Z",
      "updated_at": "2021-12-24T06:20:30.735Z",
      "position": 1,
      "description": null,
      "showcase": true,
      "start_date": "2021-03-23",
      "group_id": "73bt63kd5q9k",
      "page_id": "n8766lc3ybbs",
      "group": false,
      "only_show_if_degraded": false
    },
    {
      "id": "w0ld3nc9jvdx",
      "name": "APIs",
      "status": "operational",
      "created_at": "2018-02-01T17:15:10.342Z",
      "updated_at": "2018-02-01T17:16:31.201Z",
      "position": 1,
      "description": null,
      "showcase": false,
      "start_date": null,
      "group_id": null,
      "page_id": "n8766lc3ybbs",
      "group": true,
      "only_show_if_degraded": false,
      "components": [
        "c1zr70381q86",
        "yjqnzm0tkgsd",
        "cc6gw24m02wp",
        "dnstnjnbm2vs",
        "jnrvspydmmsd",
        "5rnsdjrhk29s",
        "ssdy05xtmgvs"
      ]
    },
    {
      "id": "yjqnzm0tkgsd",
      "name": "Confluence Cloud APIs",
      "status": "operational",
      "created_at": "2018-02-01T17:15:36.411Z",
      "updated_at": "2022-03-21T05:14:56.513Z",
      "position": 2,
      "description": null,
      "showcase": true,
      "start_date": null,
      "group_id": "w0ld3nc9jvdx",
      "page_id": "n8766lc3ybbs",
      "group": false,
      "only_show_if_degraded": false
    },
    {
      "id": "73bt63kd5q9k",
      "name": "Developer",
      "status": "operational",
      "created_at": "2018-02-01T17:21:34.889Z",
      "updated_at": "2019-05-02T04:22:45.333Z",
      "position": 2,
      "description": null,
      "showcase": false,
      "start_date": null,
      "group_id": null,
      "page_id": "n8766lc3ybbs",
      "group": true,
      "only_show_if_degraded": false,
      "components": [
        "wzmg8phvmrwh",
        "hfflf63kcp1l",
        "ccbm394hy8pk",
        "ft3y6psz31vm",
        "vb9xhz9z6zbp",
        "v19cs464rk5f",
        "pgqd9x4jl520",
        "sq83n9jrwk7c",
        "64gg59lyzrfs",
        "khz72mns34gk",
        "x9bxzb5jlltj"
      ]
    },
    {
      "id": "hfflf63kcp1l",
      "name": "Artifactory (Maven repository)",
      "status": "operational",
      "created_at": "2018-02-01T17:21:49.804Z",
      "updated_at": "2021-03-23T12:04:34.080Z",
      "position": 2,
      "description": "https://maven.atlassian.com",
      "showcase": true,
      "start_date": null,
      "group_id": "73bt63kd5q9k",
      "page_id": "n8766lc3ybbs",
      "group": false,
      "only_show_if_degraded": false
    },
    {
      "id": "g04n852g3nt6",
      "name": "App listings",
      "status": "operational",
      "created_at": "2013-12-03T00:43:13.481Z",
      "updated_at": "2021-11-05T18:32:28.193Z",
      "position": 2,
      "description": "The detailed listing page for each app",
      "showcase": true,
      "start_date": null,
      "group_id": "d0m8l367qqw5",
      "page_id": "n8766lc3ybbs",
      "group": false,
      "only_show_if_degraded": false
    },
    {
      "id": "bf9d0vz83ykr",
      "name": "Atlassian Support contact form",
      "status": "operational",
      "created_at": "2018-02-02T00:25:01.592Z",
      "updated_at": "2018-02-02T00:25:43.669Z",
      "position": 2,
      "description": null,
      "showcase": false,
      "start_date": null,
      "group_id": "jgnwrfzynh93",
      "page_id": "n8766lc3ybbs",
      "group": false,
      "only_show_if_degraded": false
    },
    {
      "id": "d0m8l367qqw5",
      "name": "Marketplace",
      "status": "partial_outage",
      "created_at": "2018-02-01T17:24:49.970Z",
      "updated_at": "2019-05-02T04:22:45.342Z",
      "position": 3,
      "description": "https://marketplace.atlassian.com and related features / APIs",
      "showcase": false,
      "start_date": null,
      "group_id": null,
      "page_id": "n8766lc3ybbs",
      "group": true,
      "only_show_if_degraded": false,
      "components": [
        "mlr76v811c20",
        "g04n852g3nt6",
        "d1hybyzmqlvq",
        "7z6w09hl9mn0",
        "ydgwbb3wn2c6",
        "kj290v20168q",
        "3t1y6724xl8q",
        "ngby5fdfj3px",
        "y1fdrctjbkx0",
        "7lx3k072bl6z",
        "hk36hlvygg2q",
        "64gk05kc0lrz",
        "1vvmngd73171",
        "wm1wfkvnffmt"
      ]
    },
    {
      "id": "cc6gw24m02wp",
      "name": "Jira Cloud APIs",
      "status": "operational",
      "created_at": "2018-02-01T17:16:54.648Z",
      "updated_at": "2021-12-08T04:17:45.496Z",
      "position": 3,
      "description": null,
      "showcase": true,
      "start_date": null,
      "group_id": "w0ld3nc9jvdx",
      "page_id": "n8766lc3ybbs",
      "group": false,
      "only_show_if_degraded": false
    },
    {
      "id": "ccbm394hy8pk",
      "name": "Create and manage apps",
      "status": "operational",
      "created_at": "2018-02-01T17:21:34.902Z",
      "updated_at": "2022-03-24T07:20:28.716Z",
      "position": 3,
      "description": "The ability to create and manage apps at https://developer.atlassian.com/apps",
      "showcase": true,
      "start_date": null,
      "group_id": "73bt63kd5q9k",
      "page_id": "n8766lc3ybbs",
      "group": false,
      "only_show_if_degraded": false
    },
    {
      "id": "d1hybyzmqlvq",
      "name": "App pricing",
      "status": "operational",
      "created_at": "2013-12-03T00:43:13.497Z",
      "updated_at": "2021-11-22T06:54:16.949Z",
      "position": 3,
      "description": "App pricing queries and updates",
      "showcase": true,
      "start_date": null,
      "group_id": "d0m8l367qqw5",
      "page_id": "n8766lc3ybbs",
      "group": false,
      "only_show_if_degraded": false
    },
    {
      "id": "xjs8wcvjw85c",
      "name": "Developer community",
      "status": "operational",
      "created_at": "2018-02-01T17:22:27.268Z",
      "updated_at": "2020-03-18T01:48:19.818Z",
      "position": 3,
      "description": "https://community.developer.atlassian.com",
      "showcase": true,
      "start_date": null,
      "group_id": "jgnwrfzynh93",
      "page_id": "n8766lc3ybbs",
      "group": false,
      "only_show_if_degraded": false
    },
    {
      "id": "dnstnjnbm2vs",
      "name": "Product Events",
      "status": "operational",
      "created_at": "2021-03-23T11:58:48.255Z",
      "updated_at": "2022-02-01T04:29:15.212Z",
      "position": 4,
      "description": "Invocation of Forge functions from product events.",
      "showcase": true,
      "start_date": "2021-03-23",
      "group_id": "w0ld3nc9jvdx",
      "page_id": "n8766lc3ybbs",
      "group": false,
      "only_show_if_degraded": false
    },
    {
      "id": "7z6w09hl9mn0",
      "name": "App submissions",
      "status": "operational",
      "created_at": "2018-02-01T17:48:45.038Z",
      "updated_at": "2022-02-16T14:36:17.510Z",
      "position": 4,
      "description": null,
      "showcase": true,
      "start_date": null,
      "group_id": "d0m8l367qqw5",
      "page_id": "n8766lc3ybbs",
      "group": false,
      "only_show_if_degraded": false
    },
    {
      "id": "fjsq71xwd3rn",
      "name": "Authentication and user management",
      "status": "operational",
      "created_at": "2019-05-02T04:22:28.554Z",
      "updated_at": "2022-01-25T12:22:54.252Z",
      "position": 4,
      "description": null,
      "showcase": true,
      "start_date": null,
      "group_id": null,
      "page_id": "n8766lc3ybbs",
      "group": false,
      "only_show_if_degraded": false
    },
    {
      "id": "ft3y6psz31vm",
      "name": "Developer documentation",
      "status": "operational",
      "created_at": "2018-02-01T17:23:24.905Z",
      "updated_at": "2021-10-06T21:03:57.450Z",
      "position": 4,
      "description": "The ability to access documentation at https://developer.atlassian.com/docs",
      "showcase": true,
      "start_date": null,
      "group_id": "73bt63kd5q9k",
      "page_id": "n8766lc3ybbs",
      "group": false,
      "only_show_if_degraded": false
    },
    {
      "id": "crfmnmkyvltr",
      "name": "Developer service desk",
      "status": "operational",
      "created_at": "2018-02-01T17:27:59.399Z",
      "updated_at": "2018-02-21T00:14:50.224Z",
      "position": 4,
      "description": "Jira Service Desk project accessible at http://go.atlassian.com/developer-support",
      "showcase": false,
      "start_date": null,
      "group_id": "jgnwrfzynh93",
      "page_id": "n8766lc3ybbs",
      "group": false,
      "only_show_if_degraded": false
    },
    {
      "id": "vb9xhz9z6zbp",
      "name": "Forge App Installation",
      "status": "operational",
      "created_at": "2021-03-23T11:55:32.639Z",
      "updated_at": "2021-03-23T12:04:48.350Z",
      "position": 5,
      "description": "Installation of Forge apps",
      "showcase": true,
      "start_date": "2021-03-23",
      "group_id": "73bt63kd5q9k",
      "page_id": "n8766lc3ybbs",
      "group": false,
      "only_show_if_degraded": false
    },
    {
      "id": "jgnwrfzynh93",
      "name": "Support",
      "status": "operational",
      "created_at": "2018-02-01T17:27:18.010Z",
      "updated_at": "2018-02-01T17:40:12.769Z",
      "position": 5,
      "description": null,
      "showcase": false,
      "start_date": null,
      "group_id": null,
      "page_id": "n8766lc3ybbs",
      "group": true,
      "only_show_if_degraded": false,
      "components": [
        "bf9d0vz83ykr",
        "xjs8wcvjw85c",
        "crfmnmkyvltr",
        "bdrd3wct69vq",
        "bqzdpnq7v22n",
        "slvmv5jvbr4p"
      ]
    },
    {
      "id": "bdrd3wct69vq",
      "name": "Marketplace service desk",
      "status": "operational",
      "created_at": "2017-07-24T21:40:38.551Z",
      "updated_at": "2018-02-21T00:14:50.256Z",
      "position": 5,
      "description": "Jira Service Desk project accessible at http://go.atlassian.com/marketplace-support",
      "showcase": false,
      "start_date": null,
      "group_id": "jgnwrfzynh93",
      "page_id": "n8766lc3ybbs",
      "group": false,
      "only_show_if_degraded": false
    },
    {
      "id": "jnrvspydmmsd",
      "name": "User APIs",
      "status": "operational",
      "created_at": "2018-02-01T17:17:26.159Z",
      "updated_at": "2021-03-23T12:03:17.254Z",
      "position": 5,
      "description": null,
      "showcase": true,
      "start_date": null,
      "group_id": "w0ld3nc9jvdx",
      "page_id": "n8766lc3ybbs",
      "group": false,
      "only_show_if_degraded": false
    },
    {
      "id": "ydgwbb3wn2c6",
      "name": "Category landing pages",
      "status": "operational",
      "created_at": "2018-03-16T16:51:24.514Z",
      "updated_at": "2021-09-29T18:05:57.225Z",
      "position": 5,
      "description": null,
      "showcase": true,
      "start_date": null,
      "group_id": "d0m8l367qqw5",
      "page_id": "n8766lc3ybbs",
      "group": false,
      "only_show_if_degraded": false
    },
    {
      "id": "v19cs464rk5f",
      "name": "Forge CDN (Custom UI)",
      "status": "operational",
      "created_at": "2021-03-23T11:57:30.618Z",
      "updated_at": "2021-03-23T12:05:08.811Z",
      "position": 6,
      "description": "Static asset serving for Forge apps.",
      "showcase": true,
      "start_date": "2021-03-23",
      "group_id": "73bt63kd5q9k",
      "page_id": "n8766lc3ybbs",
      "group": false,
      "only_show_if_degraded": false
    },
    {
      "id": "kj290v20168q",
      "name": "Evaluations and purchases",
      "status": "operational",
      "created_at": "2018-02-01T17:50:19.946Z",
      "updated_at": "2022-01-25T12:22:54.269Z",
      "position": 6,
      "description": null,
      "showcase": true,
      "start_date": null,
      "group_id": "d0m8l367qqw5",
      "page_id": "n8766lc3ybbs",
      "group": false,
      "only_show_if_degraded": false
    },
    {
      "id": "bqzdpnq7v22n",
      "name": "Atlassian Support",
      "status": "operational",
      "created_at": "2019-05-01T23:50:52.594Z",
      "updated_at": "2022-03-28T17:35:09.784Z",
      "position": 6,
      "description": null,
      "showcase": false,
      "start_date": null,
      "group_id": "jgnwrfzynh93",
      "page_id": "n8766lc3ybbs",
      "group": false,
      "only_show_if_degraded": false
    },
    {
      "id": "5rnsdjrhk29s",
      "name": "Webhooks",
      "status": "operational",
      "created_at": "2018-02-01T17:19:01.020Z",
      "updated_at": "2021-03-23T12:03:17.265Z",
      "position": 6,
      "description": null,
      "showcase": true,
      "start_date": null,
      "group_id": "w0ld3nc9jvdx",
      "page_id": "n8766lc3ybbs",
      "group": false,
      "only_show_if_degraded": false
    },
    {
      "id": "ssdy05xtmgvs",
      "name": "Web Triggers",
      "status": "operational",
      "created_at": "2021-03-23T12:00:50.143Z",
      "updated_at": "2021-03-23T12:03:17.275Z",
      "position": 7,
      "description": null,
      "showcase": true,
      "start_date": "2021-03-23",
      "group_id": "w0ld3nc9jvdx",
      "page_id": "n8766lc3ybbs",
      "group": false,
      "only_show_if_degraded": false
    },
    {
      "id": "slvmv5jvbr4p",
      "name": "Vulnerability management [AMS]",
      "status": "operational",
      "created_at": "2022-02-04T21:31:59.580Z",
      "updated_at": "2022-02-07T18:46:28.092Z",
      "position": 7,
      "description": null,
      "showcase": true,
      "start_date": "2022-02-04",
      "group_id": "jgnwrfzynh93",
      "page_id": "n8766lc3ybbs",
      "group": false,
      "only_show_if_degraded": false
    },
    {
      "id": "3t1y6724xl8q",
      "name": "In-product Marketplace and app installation (Cloud)",
      "status": "operational",
      "created_at": "2013-12-03T00:45:39.973Z",
      "updated_at": "2022-04-07T05:05:28.762Z",
      "position": 7,
      "description": "The ability to discover, install, and manage apps inside of Atlassian's Cloud products (Jira, Confluence, Stride, Bitbucket)",
      "showcase": true,
      "start_date": null,
      "group_id": "d0m8l367qqw5",
      "page_id": "n8766lc3ybbs",
      "group": false,
      "only_show_if_degraded": false
    },
    {
      "id": "pgqd9x4jl520",
      "name": "Forge Function Invocation",
      "status": "operational",
      "created_at": "2021-03-23T11:56:37.167Z",
      "updated_at": "2021-05-12T00:19:48.687Z",
      "position": 7,
      "description": null,
      "showcase": true,
      "start_date": "2021-03-23",
      "group_id": "73bt63kd5q9k",
      "page_id": "n8766lc3ybbs",
      "group": false,
      "only_show_if_degraded": false
    },
    {
      "id": "ngby5fdfj3px",
      "name": "In-product Marketplace and app installation (Server)",
      "status": "operational",
      "created_at": "2018-02-01T17:38:37.793Z",
      "updated_at": "2022-01-25T04:09:47.089Z",
      "position": 8,
      "description": "The ability to discover, install, and manage apps inside of Atlassian's Server products (Jira, Confluence, Bitbucket, Bamboo, Fisheye / Crucible, Hipchat)",
      "showcase": true,
      "start_date": null,
      "group_id": "d0m8l367qqw5",
      "page_id": "n8766lc3ybbs",
      "group": false,
      "only_show_if_degraded": false
    },
    {
      "id": "sq83n9jrwk7c",
      "name": "aui-cdn.atlassian.com",
      "status": "operational",
      "created_at": "2019-01-30T00:03:56.515Z",
      "updated_at": "2021-03-23T12:05:08.829Z",
      "position": 8,
      "description": "The Atlassian User Interface (AUI) CDN",
      "showcase": true,
      "start_date": null,
      "group_id": "73bt63kd5q9k",
      "page_id": "n8766lc3ybbs",
      "group": false,
      "only_show_if_degraded": false
    },
    {
      "id": "64gg59lyzrfs",
      "name": "Forge App Logs",
      "status": "operational",
      "created_at": "2021-05-12T00:18:57.324Z",
      "updated_at": "2021-12-08T00:00:07.000Z",
      "position": 9,
      "description": "Access and retrieve app logs via Forge CLI and admin.atlassian.com",
      "showcase": true,
      "start_date": "2021-05-12",
      "group_id": "73bt63kd5q9k",
      "page_id": "n8766lc3ybbs",
      "group": false,
      "only_show_if_degraded": false
    },
    {
      "id": "y1fdrctjbkx0",
      "name": "Notifications",
      "status": "operational",
      "created_at": "2018-02-01T17:52:26.480Z",
      "updated_at": "2020-07-09T10:30:48.498Z",
      "position": 9,
      "description": "Example notifications include newly posted reviews and new version creation",
      "showcase": true,
      "start_date": null,
      "group_id": "d0m8l367qqw5",
      "page_id": "n8766lc3ybbs",
      "group": false,
      "only_show_if_degraded": false
    },
    {
      "id": "khz72mns34gk",
      "name": "Developer console",
      "status": "operational",
      "created_at": "2021-07-09T01:52:46.683Z",
      "updated_at": "2022-04-01T00:18:53.385Z",
      "position": 10,
      "description": "Reliability of https://developer.atlassian.com/console",
      "showcase": true,
      "start_date": "2021-07-08",
      "group_id": "73bt63kd5q9k",
      "page_id": "n8766lc3ybbs",
      "group": false,
      "only_show_if_degraded": false
    },
    {
      "id": "7lx3k072bl6z",
      "name": "Private listings",
      "status": "operational",
      "created_at": "2018-02-01T17:52:40.782Z",
      "updated_at": "2022-01-25T04:09:47.102Z",
      "position": 10,
      "description": null,
      "showcase": true,
      "start_date": null,
      "group_id": "d0m8l367qqw5",
      "page_id": "n8766lc3ybbs",
      "group": false,
      "only_show_if_degraded": false
    },
    {
      "id": "hk36hlvygg2q",
      "name": "Reporting APIs and dashboards",
      "status": "degraded_performance",
      "created_at": "2013-12-03T00:45:26.014Z",
      "updated_at": "2022-04-21T05:56:00.979Z",
      "position": 11,
      "description": "Marketing attribution reports are now operational.",
      "showcase": true,
      "start_date": null,
      "group_id": "d0m8l367qqw5",
      "page_id": "n8766lc3ybbs",
      "group": false,
      "only_show_if_degraded": false
    },
    {
      "id": "x9bxzb5jlltj",
      "name": "Forge direct app distribution",
      "status": "operational",
      "created_at": "2022-03-15T10:00:31.590Z",
      "updated_at": "2022-03-23T23:18:45.625Z",
      "position": 11,
      "description": "A way to share your apps with a set of trusted site admins: https://developer.atlassian.com/platform/forge/distribute-your-apps/#start-sharing-your-app",
      "showcase": true,
      "start_date": "2022-03-15",
      "group_id": "73bt63kd5q9k",
      "page_id": "n8766lc3ybbs",
      "group": false,
      "only_show_if_degraded": false
    },
    {
      "id": "64gk05kc0lrz",
      "name": "Search",
      "status": "operational",
      "created_at": "2013-12-03T00:45:30.772Z",
      "updated_at": "2021-11-26T06:10:47.389Z",
      "position": 12,
      "description": null,
      "showcase": true,
      "start_date": null,
      "group_id": "d0m8l367qqw5",
      "page_id": "n8766lc3ybbs",
      "group": false,
      "only_show_if_degraded": false
    },
    {
      "id": "1vvmngd73171",
      "name": "Vendor management",
      "status": "partial_outage",
      "created_at": "2018-02-01T17:53:33.728Z",
      "updated_at": "2022-04-08T12:45:39.359Z",
      "position": 13,
      "description": null,
      "showcase": true,
      "start_date": null,
      "group_id": "d0m8l367qqw5",
      "page_id": "n8766lc3ybbs",
      "group": false,
      "only_show_if_degraded": false
    },
    {
      "id": "wm1wfkvnffmt",
      "name": "Vendor Home Page",
      "status": "operational",
      "created_at": "2020-01-03T14:35:08.927Z",
      "updated_at": "2020-09-07T04:56:35.634Z",
      "position": 14,
      "description": null,
      "showcase": true,
      "start_date": null,
      "group_id": "d0m8l367qqw5",
      "page_id": "n8766lc3ybbs",
      "group": false,
      "only_show_if_degraded": false
    }
  ],
  "incidents": [
    {
      "id": "sk8pvdp7j8t7",
      "name": "Delay in Licenses and Transactions data in the reporting for marketplace partners",
      "status": "identified",
      "created_at": "2022-04-21T05:56:00.939Z",
      "updated_at": "2022-04-21T05:56:01.029Z",
      "monitoring_at": null,
      "resolved_at": null,
      "impact": "minor",
      "shortlink": "https://stspg.io/k524q1yk0wg6",
      "started_at": "2022-04-21T05:56:00.931Z",
      "page_id": "n8766lc3ybbs",
      "incident_updates": [
        {
          "id": "12f05r3kzgm5",
          "status": "identified",
          "body": "The issue has been identified and a fix is being implemented.",
          "incident_id": "sk8pvdp7j8t7",
          "created_at": "2022-04-21T05:56:01.026Z",
          "updated_at": "2022-04-21T05:56:01.026Z",
          "display_at": "2022-04-21T05:56:01.026Z",
          "affected_components": [
            {
              "code": "hk36hlvygg2q",
              "name": "Marketplace - Reporting APIs and dashboards",
              "old_status": "operational",
              "new_status": "degraded_performance"
            }
          ],
          "deliver_notifications": true,
          "custom_tweet": null,
          "tweet_id": null
        }
      ],
      "components": [
        {
          "id": "hk36hlvygg2q",
          "name": "Reporting APIs and dashboards",
          "status": "degraded_performance",
          "created_at": "2013-12-03T00:45:26.014Z",
          "updated_at": "2022-04-21T05:56:00.979Z",
          "position": 11,
          "description": "Marketing attribution reports are now operational.",
          "showcase": true,
          "start_date": null,
          "group_id": "d0m8l367qqw5",
          "page_id": "n8766lc3ybbs",
          "group": false,
          "only_show_if_degraded": false
        }
      ]
    },
    {
      "id": "lc7cnnkpf3k2",
      "name": "Some marketplace partners are unable to update Partner account details on Marketplace.",
      "status": "identified",
      "created_at": "2022-04-08T12:45:39.325Z",
      "updated_at": "2022-04-12T08:24:36.056Z",
      "monitoring_at": null,
      "resolved_at": null,
      "impact": "minor",
      "shortlink": "https://stspg.io/7rs1s2vcpzdq",
      "started_at": "2022-04-08T12:45:39.317Z",
      "page_id": "n8766lc3ybbs",
      "incident_updates": [
        {
          "id": "1twqdx07225h",
          "status": "identified",
          "body": "While we have identified the root cause, we wont be able to deploy the fix as the team is working on resolving a critical outage. \nWe acknowledge that this is an inconvenience to partners and we sincerely apologise for the same. In the meanwhile, to help with updates for tiered partners we have a workaround in place, please do reach out to us [here|https://ecosystem.atlassian.net/servicedesk/customer/portal/9/group/30/create/56].",
          "incident_id": "lc7cnnkpf3k2",
          "created_at": "2022-04-12T08:24:36.054Z",
          "updated_at": "2022-04-12T08:24:36.054Z",
          "display_at": "2022-04-12T08:24:36.054Z",
          "affected_components": [
            {
              "code": "1vvmngd73171",
              "name": "Marketplace - Vendor management",
              "old_status": "partial_outage",
              "new_status": "partial_outage"
            }
          ],
          "deliver_notifications": true,
          "custom_tweet": null,
          "tweet_id": null
        },
        {
          "id": "bxnrwj1gkkzq",
          "status": "identified",
          "body": "We are continuing to fix the issue. In the meantime if you are seeing an issue updating your Partner account details , please reach to us from here[https://ecosystem.atlassian.net/servicedesk/customer/portal/9/group/30/create/56] for further assistance.",
          "incident_id": "lc7cnnkpf3k2",
          "created_at": "2022-04-08T14:16:57.881Z",
          "updated_at": "2022-04-08T14:16:57.881Z",
          "display_at": "2022-04-08T14:16:57.881Z",
          "affected_components": [
            {
              "code": "1vvmngd73171",
              "name": "Marketplace - Vendor management",
              "old_status": "partial_outage",
              "new_status": "partial_outage"
            }
          ],
          "deliver_notifications": true,
          "custom_tweet": null,
          "tweet_id": null
        },
        {
          "id": "ngdkdlhz2jrq",
          "status": "identified",
          "body": "We have identified the cause of the issue and we're working on fixing it.",
          "incident_id": "lc7cnnkpf3k2",
          "created_at": "2022-04-08T14:05:43.618Z",
          "updated_at": "2022-04-08T14:05:43.618Z",
          "display_at": "2022-04-08T14:05:43.618Z",
          "affected_components": [
            {
              "code": "1vvmngd73171",
              "name": "Marketplace - Vendor management",
              "old_status": "partial_outage",
              "new_status": "partial_outage"
            }
          ],
          "deliver_notifications": true,
          "custom_tweet": null,
          "tweet_id": null
        },
        {
          "id": "68yx19yk19wp",
          "status": "investigating",
          "body": "We have identified an issue where some marketplace partners are unable to update their partner account details. Our developers are working to resolve the issue.",
          "incident_id": "lc7cnnkpf3k2",
          "created_at": "2022-04-08T12:45:39.398Z",
          "updated_at": "2022-04-08T12:45:39.398Z",
          "display_at": "2022-04-08T12:45:39.398Z",
          "affected_components": [
            {
              "code": "1vvmngd73171",
              "name": "Marketplace - Vendor management",
              "old_status": "operational",
              "new_status": "partial_outage"
            }
          ],
          "deliver_notifications": true,
          "custom_tweet": null,
          "tweet_id": null
        }
      ],
      "components": [
        {
          "id": "1vvmngd73171",
          "name": "Vendor management",
          "status": "partial_outage",
          "created_at": "2018-02-01T17:53:33.728Z",
          "updated_at": "2022-04-08T12:45:39.359Z",
          "position": 13,
          "description": null,
          "showcase": true,
          "start_date": null,
          "group_id": "d0m8l367qqw5",
          "page_id": "n8766lc3ybbs",
          "group": false,
          "only_show_if_degraded": false
        }
      ]
    }
  ],
  "scheduled_maintenances": [],
  "status": {
    "indicator": "minor",
    "description": "Minor Service Outage"
  }
}
