{
  "page": {
    "id": "bqlf8qjztdtr",
    "name": "Atlassian Bitbucket",
    "url": "https://bitbucket.status.atlassian.com",
    "time_zone": "Etc/UTC",
    "updated_at": "2023-12-18T16:06:04.155Z"
  },
  "components": [
    {
      "id": "g0lfj4sv2fhf",
      "name": "Website",
      "status": "operational",
      "created_at": "2013-09-26T03:34:27.377Z",
      "updated_at": "2023-12-09T23:27:01.560Z",
      "position": 1,
      "description": "Access to bitbucket.org",
      "showcase": false,
      "start_date": null,
      "group_id": null,
      "page_id": "bqlf8qjztdtr",
      "group": false,
      "only_show_if_degraded": false
    },
    {
      "id": "k0x2yw1435v7",
      "name": "API",
      "status": "operational",
      "created_at": "2015-06-05T19:34:43.541Z",
      "updated_at": "2023-12-09T23:27:01.591Z",
      "position": 2,
      "description": "Access to api.bitbucket.org",
      "showcase": false,
      "start_date": null,
      "group_id": null,
      "page_id": "bqlf8qjztdtr",
      "group": false,
      "only_show_if_degraded": false
    },
    {
      "id": "qmh4tj8h5kbn",
      "name": "Git via SSH",
      "status": "operational",
      "created_at": "2013-10-10T17:45:00.679Z",
      "updated_at": "2023-12-09T23:27:01.617Z",
      "position": 3,
      "description": "Access to Git over SSH.",
      "showcase": false,
      "start_date": null,
      "group_id": null,
      "page_id": "bqlf8qjztdtr",
      "group": false,
      "only_show_if_degraded": false
    },
    {
      "id": "qfsxh5mgnyyn",
      "name": "Authentication and user management",
      "status": "operational",
      "created_at": "2019-05-02T04:19:58.553Z",
      "updated_at": "2023-12-09T23:27:01.644Z",
      "position": 4,
      "description": null,
      "showcase": false,
      "start_date": null,
      "group_id": null,
      "page_id": "bqlf8qjztdtr",
      "group": false,
      "only_show_if_degraded": false
    },
    {
      "id": "c1qmcrcbc5zy",
      "name": "Git via HTTPS",
      "status": "operational",
      "created_at": "2013-09-26T03:33:27.652Z",
      "updated_at": "2023-12-09T23:27:01.673Z",
      "position": 5,
      "description": "Access to Git repositories via HTTPS",
      "showcase": false,
      "start_date": null,
      "group_id": null,
      "page_id": "bqlf8qjztdtr",
      "group": false,
      "only_show_if_degraded": false
    },
    {
      "id": "rfzky0v13fbp",
      "name": "Webhooks",
      "status": "operational",
      "created_at": "2015-07-29T01:37:04.511Z",
      "updated_at": "2023-12-09T23:27:01.702Z",
      "position": 7,
      "description": "The Bitbucket webhooks service",
      "showcase": false,
      "start_date": null,
      "group_id": null,
      "page_id": "bqlf8qjztdtr",
      "group": false,
      "only_show_if_degraded": false
    },
    {
      "id": "28h8dvv2qfzw",
      "name": "Source downloads",
      "status": "operational",
      "created_at": "2013-09-26T05:30:21.132Z",
      "updated_at": "2023-12-09T23:27:01.728Z",
      "position": 8,
      "description": "Archive (zip, tar.gz, bzip) downloads of repositories",
      "showcase": false,
      "start_date": null,
      "group_id": null,
      "page_id": "bqlf8qjztdtr",
      "group": false,
      "only_show_if_degraded": false
    },
    {
      "id": "rzh2n85q7vtt",
      "name": "Pipelines",
      "status": "operational",
      "created_at": "2016-08-23T20:04:54.469Z",
      "updated_at": "2023-12-09T23:27:01.753Z",
      "position": 9,
      "description": "Continuous integration and delivery for Bitbucket repos",
      "showcase": false,
      "start_date": null,
      "group_id": null,
      "page_id": "bqlf8qjztdtr",
      "group": false,
      "only_show_if_degraded": false
    },
    {
      "id": "g0c8l3nn2vr1",
      "name": "Git LFS",
      "status": "operational",
      "created_at": "2017-03-06T20:22:58.463Z",
      "updated_at": "2023-12-09T23:27:01.769Z",
      "position": 10,
      "description": "Git Large File Storage",
      "showcase": false,
      "start_date": null,
      "group_id": null,
      "page_id": "bqlf8qjztdtr",
      "group": false,
      "only_show_if_degraded": false
    },
    {
      "id": "vc7m6mtqmxf9",
      "name": "Email delivery",
      "status": "operational",
      "created_at": "2016-08-31T21:24:07.594Z",
      "updated_at": "2023-12-09T23:27:01.784Z",
      "position": 11,
      "description": null,
      "showcase": false,
      "start_date": null,
      "group_id": null,
      "page_id": "bqlf8qjztdtr",
      "group": false,
      "only_show_if_degraded": false
    },
    {
      "id": "3hz4wpmhhqxx",
      "name": "Purchasing & Licensing",
      "status": "operational",
      "created_at": "2020-04-28T00:49:02.407Z",
      "updated_at": "2023-12-09T23:27:01.799Z",
      "position": 13,
      "description": null,
      "showcase": false,
      "start_date": null,
      "group_id": null,
      "page_id": "bqlf8qjztdtr",
      "group": false,
      "only_show_if_degraded": false
    },
    {
      "id": "tmjhkbvskftr",
      "name": "Signup",
      "status": "operational",
      "created_at": "2020-10-09T20:39:28.376Z",
      "updated_at": "2023-12-09T23:27:01.825Z",
      "position": 14,
      "description": null,
      "showcase": false,
      "start_date": "2020-10-09",
      "group_id": null,
      "page_id": "bqlf8qjztdtr",
      "group": false,
      "only_show_if_degraded": false
    }
  ],
  "incidents": [
    {
      "id": "v6lg728gnck0",
      "name": "Atlassian's cross product user search service is currently degraded.",
      "status": "investigating",
      "created_at": "2023-12-18T15:04:25.455Z",
      "updated_at": "2023-12-18T16:06:04.143Z",
      "monitoring_at": null,
      "resolved_at": null,
      "impact": "none",
      "shortlink": "https://stspg.io/pmr9pf7c2f0f",
      "started_at": "2023-12-18T15:04:25.447Z",
      "page_id": "bqlf8qjztdtr",
      "incident_updates": [
        {
          "id": "fsjwqghlszhp",
          "status": "investigating",
          "body": "Atlassian's cross product user search service is recovering. Searches for users within Atlassian products are returning to normal.",
          "incident_id": "v6lg728gnck0",
          "created_at": "2023-12-18T16:06:04.141Z",
          "updated_at": "2023-12-18T16:06:04.141Z",
          "display_at": "2023-12-18T16:06:04.141Z",
          "affected_components": null,
          "deliver_notifications": true,
          "custom_tweet": null,
          "tweet_id": null
        },
        {
          "id": "t5z3zb6624ht",
          "status": "investigating",
          "body": "Atlassian's cross product user search service is recovering. Searches for users within Atlassian products are returning to normal.",
          "incident_id": "v6lg728gnck0",
          "created_at": "2023-12-18T16:02:08.230Z",
          "updated_at": "2023-12-18T16:02:08.230Z",
          "display_at": "2023-12-18T16:02:08.230Z",
          "affected_components": null,
          "deliver_notifications": true,
          "custom_tweet": null,
          "tweet_id": null
        },
        {
          "id": "jg7p9vsdfqwc",
          "status": "investigating",
          "body": "Atlassian's cross product user search service is recovering. Searches for users within Atlassian products are returning to normal.",
          "incident_id": "v6lg728gnck0",
          "created_at": "2023-12-18T16:01:25.726Z",
          "updated_at": "2023-12-18T16:01:25.726Z",
          "display_at": "2023-12-18T16:01:25.726Z",
          "affected_components": null,
          "deliver_notifications": true,
          "custom_tweet": null,
          "tweet_id": null
        },
        {
          "id": "nkz69d5w5t68",
          "status": "investigating",
          "body": "We are investigating reports of intermittent errors for <SOME/ALL> Atlassian, Confluence, Jira Work Management, Jira Service Management, Jira Software, Atlassian Bitbucket, Jira Align, Jira Product Discovery, Atlas, and Compass Cloud customers. We will provide more details once we identify the root cause.",
          "incident_id": "v6lg728gnck0",
          "created_at": "2023-12-18T15:04:25.499Z",
          "updated_at": "2023-12-18T15:04:25.499Z",
          "display_at": "2023-12-18T15:04:25.499Z",
          "affected_components": null,
          "deliver_notifications": false,
          "custom_tweet": null,
          "tweet_id": null
        }
      ],
      "components": [],
      "reminder_intervals": null
    }
  ],
  "scheduled_maintenances": [],
  "status": {
    "indicator": "none",
    "description": "All Systems Operational"
  }
}
